frida_ui/__init__.py
frida_ui/server.py
frida_ui/modules/__init__.py
frida_ui/modules/codeshare.py
frida_ui/modules/frida_manager.py
frida_ui/static/favicon.ico
frida_ui/static/index.html
frida_ui/static/script.js
frida_ui/static/styles.css
frida_ui-1.1.0.dist-info/licenses/LICENSE
frida_ui-1.1.0.dist-info/METADATA
frida_ui-1.1.0.dist-info/WHEEL
frida_ui-1.1.0.dist-info/entry_points.txt
frida_ui-1.1.0.dist-info/top_level.txt
frida_ui-1.1.0.dist-info/RECORD
