Metadata-Version: 2.4
Name: frida-ui
Version: 1.1.0
Summary: Interact with Frida devices, processes, and scripts directly from your browser.
Home-page: https://github.com/adityatelange/frida-ui
Download-URL: https://github.com/adityatelange/frida-ui/archive/v1.1.0.zip
Author: adityatelange
License: MIT
Classifier: Programming Language :: Python :: 3
Classifier: License :: OSI Approved :: MIT License
Classifier: Operating System :: OS Independent
Requires-Python: >=3.7
License-File: LICENSE
Requires-Dist: fastapi
Requires-Dist: uvicorn
Requires-Dist: frida
Requires-Dist: pydantic
Dynamic: author
Dynamic: classifier
Dynamic: description
Dynamic: description-content-type
Dynamic: download-url
Dynamic: home-page
Dynamic: license
Dynamic: license-file
Dynamic: requires-dist
Dynamic: requires-python
Dynamic: summary
